{
    "basic_info": {
      "name": "Trevor Hensel",
      "titles": [ "Team Leader", "Sr. Full Stack Developer", "Team Player" ],
      "social": [
        {
          "name": "github",
          "url": "https://github.com/TrevorHensel",
          "class": "devicon-github-original"
        },
        {
          "name": "LinkedIn",
          "url": "https://www.linkedin.com/in/trevorhensel/",
          "class": "devicon-linkedin-plain"
        }
      ],
      "image": "myProfile.jpg"
    },
    "skills": {
      "icons": [
        {
          "name": "Java",
          "class": "devicon-java-plain"
        },
        {
          "name": "Azure",
          "class": "devicon-azure-plain"
        },
        {
          "name": "Terraform",
          "class": "devicon-terraform-plain"
        },
        {
          "name": "React",
          "class": "devicon-react-original"
        },
        {
          "name": "Prometheus",
          "class": "devicon-prometheus-original"
        },
        {
          "name": "SQL",
          "class": "devicon-microsoftsqlserver-plain"
        },
        {
          "name": "MongoDB",
          "class": "devicon-mongodb-plain"
        },
        {
          "name": "Spring",
          "class": "devicon-spring-plain"
        },
        {
          "name": "DevOps",
          "class": "devicon-devicon-plain"
        },
        {
          "name": "JavaScript",
          "class": "devicon-javascript-plain"
        }
      ]
    }
  }